Metadata-Version: 1.0
Name: comentarios-variados
Version: 1.0
Summary: UNKNOWN
Home-page: UNKNOWN
Author: Eduardo Silva de Abreu
Author-email: edwards.s.a@hotmail.com
License: UNKNOWN
Keywords: comentarios,listas
Platform: UNKNOWN
